Metadata-Version: 2.1
Name: django-nats-nkeys
Version: 0.10.1
Summary: Django NATS Nkey is a Django app to synchronize Django superusers, accounts, and users with NATS nkey-based authentization/authorization scheme
Home-page: http://github.com/bitsy-ai/django-nats-nkey
Author: Leigh Johnson
Author-email: leigh@bitsy.ai
License: GNU AGPLv3
Keywords: django NATS
Platform: UNKNOWN
Classifier: Programming Language :: Python :: 3.9
Classifier: Programming Language :: Python :: 3.10
Classifier: Programming Language :: Python :: 3.11
Classifier: Framework :: Django
Classifier: Framework :: Django :: 3.1
Classifier: Framework :: Django :: 3.2
Classifier: Framework :: Django :: 4.0
Classifier: Framework :: Django :: 4.1
Requires-Python: >3.6.9
License-File: LICENSE
Requires-Dist: coolname
Requires-Dist: django
Requires-Dist: django-extensions
Requires-Dist: django-organizations
Requires-Dist: nats-py[nkeys]
Requires-Dist: psycopg2
Provides-Extra: drf
Requires-Dist: djangorestframework ; extra == 'drf'
